projectfastapi/__init__.py
projectfastapi/main.py
projectfastapi/source.py
create_app_fastapi-0.1.6.dist-info/METADATA
create_app_fastapi-0.1.6.dist-info/WHEEL
create_app_fastapi-0.1.6.dist-info/entry_points.txt
create_app_fastapi-0.1.6.dist-info/top_level.txt
create_app_fastapi-0.1.6.dist-info/RECORD
