Metadata-Version: 2.1
Name: create-app-fastapi
Version: 0.1.6
Summary: Library for initializing FastAPI project structure - create-app-fastapi
Home-page: https://github.com/ravishnu60/create-app-fastapi.git
Author: Ravishnu
Author-email: ravishnu60@gmail.com
Keywords: create-app-fastapi,create,fastapi,fastapi project,project structure,api structure,python fastapi project structure
Requires-Python: >=3.9
Requires-Dist: requests
